aether/__init__.py
aether/main.py
aether/cli/__init__.py
aether/cli/commands.py
aether/core/__init__.py
aether/core/config.py
aether/core/learning.py
aether/core/logger.py
aether_linux-1.0.3.dist-info/METADATA
aether_linux-1.0.3.dist-info/WHEEL
aether_linux-1.0.3.dist-info/entry_points.txt
aether_linux-1.0.3.dist-info/top_level.txt
aether_linux-1.0.3.dist-info/RECORD
