Metadata-Version: 2.4
Name: aether-linux
Version: 1.0.3
Summary: Una herramienta CLI para monitorear y optimizar tu sistema con estilo.
Author: Zaid Gonzalez
License: MIT
Requires-Python: >=3.8
Requires-Dist: rich
Requires-Dist: psutil
Requires-Dist: pyfiglet
Requires-Dist: colorama
